{"assets":{"4BC345470DD36222E51895BBCE5E997C":{"type":"texture","index":0,"url":{"native":"assets\/E31D701F-99AC-4283-859E-1FFA80F1DB9D.pdf"},"width":1920,"height":1080},"2EDD4895E1AE3953B57B18AD64EAFAAE":{"type":"texture","index":1,"url":{"native":"assets\/E31D701F-99AC-4283-859E-1FFA80F1DB9D.pdf"},"width":1920,"height":1080}},"events":[{"effects":[{"beginTime":0,"baseLayer":{"animations":[],"initialState":{"affineTransform":[1,0,0,1,0,0],"masksToBounds":false,"rotation":0,"scale":1,"position":{"pointX":960,"pointY":540},"width":1920,"sublayerTransform":[1,0,0,0,0,1,0,0,0,0,1,0,0,0,0,1],"contentsRect":{"y":0,"x":0,"width":1,"height":1},"opacity":1,"edgeAntialiasingMask":251658240,"height":1080,"hidden":false,"anchorPoint":{"pointX":0.5,"pointY":0.5}},"objectID":"0","layers":[{"animations":[],"initialState":{"affineTransform":[1,0,0,1,0,0],"masksToBounds":false,"rotation":0,"scale":1,"position":{"pointX":960,"pointY":540},"width":1920,"sublayerTransform":[1,0,0,0,0,1,0,0,0,0,1,-0.00035007912466775983,0,0,0,1],"contentsRect":{"y":0,"x":0,"width":1,"height":1},"opacity":1,"edgeAntialiasingMask":251658240,"height":1080,"hidden":false,"anchorPoint":{"pointX":0.5,"pointY":0.5}},"layers":[{"animations":[],"layers":[],"texturedRectangle":{"isBackgroundTexture":false,"singleTextureOpacity":1,"textureType":0,"textBaseline":0,"textXHeight":0,"isVerticalText":false},"initialState":{"affineTransform":[1,0,0,1,0,0],"masksToBounds":false,"rotation":0,"scale":1,"position":{"pointX":960,"pointY":540},"width":1920,"sublayerTransform":[1,0,0,0,0,1,0,0,0,0,1,0,0,0,0,1],"contentsRect":{"y":0,"x":0,"width":1,"height":1},"opacity":1,"edgeAntialiasingMask":0,"height":1080,"hidden":false,"anchorPoint":{"pointX":0.5,"pointY":0.5}},"texture":"2EDD4895E1AE3953B57B18AD64EAFAAE"},{"animations":[{"additive":false,"timeOffset":0,"beginTime":0,"from":{"scalar":false},"repeatCount":0,"fillMode":"both","duration":0.01,"autoreverses":false,"property":"hidden","to":{"scalar":true},"removedOnCompletion":false}],"layers":[],"texturedRectangle":{"isBackgroundTexture":false,"singleTextureOpacity":1,"textureType":0,"textBaseline":0,"textXHeight":0,"isVerticalText":false},"initialState":{"affineTransform":[1,0,0,1,0,0],"masksToBounds":false,"rotation":0,"scale":1,"position":{"pointX":960,"pointY":540},"width":1920,"sublayerTransform":[1,0,0,0,0,1,0,0,0,0,1,0,0,0,0,1],"contentsRect":{"y":0,"x":0,"width":1,"height":1},"opacity":1,"edgeAntialiasingMask":0,"height":1080,"hidden":false,"anchorPoint":{"pointX":0.5,"pointY":0.5}},"texture":"4BC345470DD36222E51895BBCE5E997C"}]}]},"effects":[],"duration":0.01,"type":"transition","attributes":{"direction":0},"name":"none","objectID":"0"}],"automaticPlay":false,"hyperlinks":[],"accessibility":[{"text":"Impact of Penalty Parameter M - 2","targetRectangle":{"y":67.065775532069097,"x":344.86799430847168,"width":1231.104000600815,"height":126.15999829769135}},{"text":"M is very negative","targetRectangle":{"y":283.36313844538728,"x":130.47920055156959,"width":380.11599999999999,"height":65.559999108314514}},{"text":"Strong penalty for infeasible points","targetRectangle":{"y":342.80713697148366,"x":173.47920007473243,"width":561.40000000000009,"height":76.649999290704727}},{"text":"cKG becomes overly conservative, avoids boundary regions","targetRectangle":{"y":414.54213578713939,"x":173.47920007473243,"width":661.81500000000005,"height":124.3849981063604}},{"text":"Fails to explore areas near constraint limits","targetRectangle":{"y":534.01213341845084,"x":173.47920007473243,"width":680.78500000000008,"height":76.649999290704727}},{"text":"Adaptive M","targetRectangle":{"y":658.08956222144968,"x":602.02441548605998,"width":245.82799999999997,"height":65.559999108314514}},{"text":"￼","targetRectangle":{"y":717.53356074754606,"x":602.02441548605998,"width":238.03574713113971,"height":105.21824380341275}},{"text":"Always prefers feasible over infeasiblecKG ignores constraints completely","targetRectangle":{"y":814.97997894351897,"x":645.02441500922282,"width":675.25499999999988,"height":124.3849981063604}},{"text":"Still explores near constraint boundary","targetRectangle":{"y":934.44997657483043,"x":645.02441500922282,"width":619.53500000000008,"height":76.649999290704727}},{"text":"M is too large","targetRectangle":{"y":283.36313817243888,"x":991.32468205916132,"width":288.41999999999996,"height":65.559999108314514}},{"text":"Infeasible points treated as good as optimal ones","targetRectangle":{"y":342.80713669853526,"x":1034.324681582324,"width":704.7950000000003,"height":124.38499810636046}},{"text":"cKG ignores constraints completely","targetRectangle":{"y":462.27713432984672,"x":1034.324681582324,"width":565.5300000000002,"height":76.649999290704727}},{"text":"Recommends only infeasible solutions","targetRectangle":{"y":534.0121331455025,"x":1034.324681582324,"width":607.74000000000024,"height":76.649999290704727}},{"text":"equation.pdf","targetRectangle":{"y":741.53356074754606,"x":602.02441548605998,"width":238.03574713113971,"height":81.218243803412747}},{"text":"￼","targetRectangle":{"y":1004.000048160553,"x":947.14999958053522,"width":25.700000000000045,"height":25.799999594688416}}],"baseLayer":{"animations":[],"initialState":{"affineTransform":[1,0,0,1,0,0],"masksToBounds":false,"rotation":0,"scale":1,"position":{"pointX":960,"pointY":540},"width":1920,"sublayerTransform":[1,0,0,0,0,1,0,0,0,0,1,0,0,0,0,1],"contentsRect":{"y":0,"x":0,"width":1,"height":1},"opacity":1,"edgeAntialiasingMask":251658240,"height":1080,"hidden":false,"anchorPoint":{"pointX":0.5,"pointY":0.5}},"objectID":"0","layers":[{"animations":[],"initialState":{"affineTransform":[1,0,0,1,0,0],"masksToBounds":false,"rotation":0,"scale":1,"position":{"pointX":960,"pointY":540},"width":1920,"sublayerTransform":[1,0,0,0,0,1,0,0,0,0,1,-0.00035007912466775983,0,0,0,1],"contentsRect":{"y":0,"x":0,"width":1,"height":1},"opacity":1,"edgeAntialiasingMask":251658240,"height":1080,"hidden":false,"anchorPoint":{"pointX":0.5,"pointY":0.5}},"layers":[{"animations":[],"layers":[],"texturedRectangle":{"isBackgroundTexture":false,"singleTextureOpacity":1,"textureType":0,"textBaseline":0,"textXHeight":0,"isVerticalText":false},"initialState":{"affineTransform":[1,0,0,1,0,0],"masksToBounds":false,"rotation":0,"scale":1,"position":{"pointX":960,"pointY":540},"width":1920,"sublayerTransform":[1,0,0,0,0,1,0,0,0,0,1,0,0,0,0,1],"contentsRect":{"y":0,"x":0,"width":1,"height":1},"opacity":1,"edgeAntialiasingMask":0,"height":1080,"hidden":false,"anchorPoint":{"pointX":0.5,"pointY":0.5}},"texture":"4BC345470DD36222E51895BBCE5E997C"}]}]}}]}